Metadata-Version: 1.0
Name: fundamental-distributions
Version: 0.1
Summary: Gaussian and Binomial distributions
Home-page: UNKNOWN
Author: Rohan Gawade
Author-email: rohangawade.18@gmail.com
License: UNKNOWN
Platform: UNKNOWN
